README.rst
setup.py
goldenarch/__init__.py
goldenarch/core.py
goldenarch.egg-info/PKG-INFO
goldenarch.egg-info/SOURCES.txt
goldenarch.egg-info/dependency_links.txt
goldenarch.egg-info/entry_points.txt
goldenarch.egg-info/requires.txt
goldenarch.egg-info/top_level.txt